visapi/__init__.py
visapi/__main__.py
visapi/app.py
visapi/context.py
visapi/exceptions.py
visapi/config/__init__.py
visapi/http/__init__.py
visapi/routing/__init__.py
visapi/routing/convertor.py
visapi/routing/route.py
visapi/routing/router.py
visapi/utils/__init__.py
visapi/utils/arguments.py
visapi-0.0.0.dist-info/LICENSE
visapi-0.0.0.dist-info/METADATA
visapi-0.0.0.dist-info/WHEEL
visapi-0.0.0.dist-info/entry_points.txt
visapi-0.0.0.dist-info/top_level.txt
visapi-0.0.0.dist-info/RECORD
