Metadata-Version: 2.1
Name: visapi
Version: 0.0.0
Summary: VisAPI, Is A Development Friendly Web Framework With Python 3.8+
Author-email: Vank <852003793@qq.com>
License: Apache License
Project-URL: Homepage, https://github.com/vanker-x/visapi
Classifier: Programming Language :: Python :: 3
Classifier: License :: OSI Approved :: Apache Software License
Classifier: Operating System :: MacOS
Classifier: Operating System :: POSIX :: Linux
Classifier: Operating System :: Microsoft :: Windows
Classifier: Topic :: Internet :: WWW/HTTP
Requires-Python: >=3.8
License-File: LICENSE
Requires-Dist: granian
